fandom_scraper/__init__.py
fandom_scraper/fandom_scraper.py
fandom_scraper/witcher_instruct_gather.py
fandom_scraper-0.6.4.dist-info/WHEEL
fandom_scraper-0.6.4.dist-info/entry_points.txt
fandom_scraper-0.6.4.dist-info/METADATA
fandom_scraper-0.6.4.dist-info/RECORD
